MANIFEST.in
README
setup.py
django_netauth.egg-info/PKG-INFO
django_netauth.egg-info/SOURCES.txt
django_netauth.egg-info/dependency_links.txt
django_netauth.egg-info/requires.txt
django_netauth.egg-info/top_level.txt
example_project/__init__.py
example_project/manage.py
example_project/wsgi.py
example_project/main/__init__.py
example_project/main/models.py
example_project/main/urls.py
example_project/main/views.py
example_project/main/tests/__init__.py
example_project/main/tests/base.py
example_project/main/tests/client.py
example_project/main/tests/netauth_test.py
example_project/settings/__init__.py
example_project/settings/core.py
example_project/settings/dev.py
example_project/settings/project.py
example_project/settings/test.py
netauth/__init__.py
netauth/__init__.pyc
netauth/admin.py
netauth/auth.py
netauth/forms.py
netauth/lang.py
netauth/models.py
netauth/settings.py
netauth/urls.py
netauth/utils.py
netauth/views.py
netauth/backends/__init__.py
netauth/backends/facebook.py
netauth/backends/google.py
netauth/backends/oauth.py
netauth/backends/openid.py
netauth/backends/vkontakte.py
netauth/backends/yandex.py
netauth/static/netauth/css/main.css
netauth/static/netauth/images/providers_sprite.png
netauth/templates/netauth/extra.html
netauth/templates/netauth/login.html
netauth/templates/netauth/widget.html
netauth/templates/netauth/yandex_proxy.html
netauth/templates/netauth/mail/registration.txt
netauth/templates/netauth/mail/reset_password.txt
netauth/templatetags/__init__.py
netauth/templatetags/netauth_tags.py