Metadata-Version: 1.0
Name: django-netauth
Version: 0.1.94
Summary: Django openid, oauth authentification.
